setup.py
executor/executor.py
executor/ndmspc-executor.py
ndmspc_api.egg-info/PKG-INFO
ndmspc_api.egg-info/SOURCES.txt
ndmspc_api.egg-info/dependency_links.txt
ndmspc_api.egg-info/requires.txt
ndmspc_api.egg-info/top_level.txt