Metadata-Version: 2.1
Name: ndmspc-api
Version: 0.0.2
Summary: FastAPI Executor API
Home-page: https://gitlab.com/ndmspc/api
Author: Dominik Matis
Author-email: domosino44@gmail.com
License: BSD 2-clause
Platform: UNKNOWN
